maturin/__init__.py
maturin/__main__.py
maturin_qpython-1.7.4.dist-info/METADATA
maturin_qpython-1.7.4.dist-info/WHEEL
maturin_qpython-1.7.4.dist-info/top_level.txt
maturin_qpython-1.7.4.dist-info/RECORD
